pythondata_cpu_blackparrot/__init__.py
pythondata_cpu_blackparrot/system_verilog/.gitignore
pythondata_cpu_blackparrot/system_verilog/.gitlab-ci.yml
pythondata_cpu_blackparrot/system_verilog/.gitmodules
pythondata_cpu_blackparrot/system_verilog/CONTRIBUTING.md
pythondata_cpu_blackparrot/system_verilog/GETTING_STARTED.md
pythondata_cpu_blackparrot/system_verilog/LICENSE
pythondata_cpu_blackparrot/system_verilog/Makefile
pythondata_cpu_blackparrot/system_verilog/Makefile.common
pythondata_cpu_blackparrot/system_verilog/README.md
pythondata_cpu_blackparrot/system_verilog/STYLE_GUIDE.md
pythondata_cpu_blackparrot/system_verilog/bp_be/.gitignore
pythondata_cpu_blackparrot/system_verilog/bp_be/README.md
pythondata_cpu_blackparrot/system_verilog/bp_be/software/py/hex2binascii.py
pythondata_cpu_blackparrot/system_verilog/bp_be/software/py/spike2tr.py
pythondata_cpu_blackparrot/system_verilog/bp_be/src/include/bp_be_ctl_defines.vh
pythondata_cpu_blackparrot/system_verilog/bp_be/src/include/bp_be_internal_if_defines.vh
pythondata_cpu_blackparrot/system_verilog/bp_be/src/include/bp_be_mem_defines.vh
pythondata_cpu_blackparrot/system_verilog/bp_be/src/include/bp_be_pkg.vh
pythondata_cpu_blackparrot/system_verilog/bp_be/src/include/bp_be_dcache/bp_be_dcache_lce_pkt.vh
pythondata_cpu_blackparrot/system_verilog/bp_be/src/include/bp_be_dcache/bp_be_dcache_pkg.vh
pythondata_cpu_blackparrot/system_verilog/bp_be/src/include/bp_be_dcache/bp_be_dcache_pkt.vh
pythondata_cpu_blackparrot/system_verilog/bp_be/src/include/bp_be_dcache/bp_be_dcache_stat_info.vh
pythondata_cpu_blackparrot/system_verilog/bp_be/src/include/bp_be_dcache/bp_be_dcache_tag_info.vh
pythondata_cpu_blackparrot/system_verilog/bp_be/src/include/bp_be_dcache/bp_be_dcache_wbuf_entry.vh
pythondata_cpu_blackparrot/system_verilog/bp_be/src/v/bp_be_top.v
pythondata_cpu_blackparrot/system_verilog/bp_be/src/v/bp_be_calculator/bp_be_bypass.v
pythondata_cpu_blackparrot-0.0.post1817.dist-info/LICENSE
pythondata_cpu_blackparrot-0.0.post1817.dist-info/METADATA
pythondata_cpu_blackparrot-0.0.post1817.dist-info/WHEEL
pythondata_cpu_blackparrot-0.0.post1817.dist-info/top_level.txt
pythondata_cpu_blackparrot-0.0.post1817.dist-info/RECORD
