Metadata-Version: 2.1
Name: pythondata-cpu-blackparrot
Version: 0.0.post1817
Summary: Python module containing system_verilog files for BlackParrot cpu.
Home-page: https://github.com/litex-hub/pythondata-cpu-blackparrot
Author: LiteX Authors
Author-email: litex@googlegroups.com
License: UNKNOWN
Project-URL: Bug Tracker, https://github.com/litex-hub/pythondata-cpu-blackparrot/issues
Project-URL: Source Code, https://github.com/litex-hub/pythondata-cpu-blackparrot
Platform: UNKNOWN
Classifier: Programming Language :: Python :: 3
Classifier: License :: OSI Approved :: BSD License
Classifier: Operating System :: OS Independent
Requires-Python: >=3.5
